oerplib/__init__.py
oerplib/error.py
oerplib/oerp.py
oerplib/rpc/__init__.py
oerplib/rpc/error.py
oerplib/rpc/jsonrpclib.py
oerplib/rpc/netrpclib.py
oerplib/rpc/service.py
oerplib/rpc/xmlrpclib_custom.py
oerplib/service/__init__.py
oerplib/service/common.py
oerplib/service/db.py
oerplib/service/wizard.py
oerplib/service/inspect/__init__.py
oerplib/service/inspect/dependencies.py
oerplib/service/inspect/on_change.py
oerplib/service/inspect/relations.py
oerplib/service/osv/__init__.py
oerplib/service/osv/browse.py
oerplib/service/osv/fields.py
oerplib/service/osv/osv.py
oerplib/tools/__init__.py
oerplib/tools/session.py
OERPLib_py3-0.8.6.dist-info/AUTHORS.txt
OERPLib_py3-0.8.6.dist-info/LICENSE.txt
OERPLib_py3-0.8.6.dist-info/METADATA
OERPLib_py3-0.8.6.dist-info/WHEEL
OERPLib_py3-0.8.6.dist-info/top_level.txt
OERPLib_py3-0.8.6.dist-info/RECORD
