Metadata-Version: 2.1
Name: OERPLib-py3
Version: 0.8.6
Summary: OERPLib-py3 is a Python module providing an easy way to pilot your OpenERP and Odoo servers through RPC.
Home-page: http://pythonhosted.org/OERPLib-py3/
Download-URL: http://pypi.python.org/packages/source/O/OERPLib-py3/OERPLib-py3-0.8.6.tar.gz
Author: ABF Osiell - Sebastien Alix
Author-email: sebastien.alix@osiell.com
License: LGPL v3
Keywords: openerp odoo server client xml-rpc xmlrpc net-rpc netrpc oerplib communication lib library python service web webservice
Platform: UNKNOWN
Classifier: Intended Audience :: Developers
Classifier: Programming Language :: Python
Classifier: Programming Language :: Python :: 2.6
Classifier: Programming Language :: Python :: 2.7
Classifier: Programming Language :: Python :: 3.8
Classifier: Programming Language :: Python :: Implementation :: CPython
Classifier: License :: OSI Approved :: GNU Library or Lesser General Public License (LGPL)
Classifier: Topic :: Software Development :: Libraries :: Python Modules
License-File: LICENSE.txt
License-File: AUTHORS.txt
